{
  "id": "aba285b9-6af4-4af9-bc5d-909664d1653a",
  "prevId": "c8c21883-afdd-44d5-88c7-96954de240ca",
  "version": "7",
  "dialect": "postgresql",
  "tables": {
    "public.app_settings": {
      "name": "app_settings",
      "schema": "",
      "columns": {
        "id": {
          "name": "id",
          "type": "text",
          "primaryKey": true,
          "notNull": true
        },
        "key": {
          "name": "key",
          "type": "text",
          "primaryKey": false,
          "notNull": true
        },
        "value": {
          "name": "value",
          "type": "text",
          "primaryKey": false,
          "notNull": true
        },
        "created_at": {
          "name": "created_at",
          "type": "timestamp",
          "primaryKey": false,
          "notNull": false,
          "default": "now()"
        },
        "updated_at": {
          "name": "updated_at",
          "type": "timestamp",
          "primaryKey": false,
          "notNull": false,
          "default": "now()"
        }
      },
      "indexes": {},
      "foreignKeys": {},
      "compositePrimaryKeys": {},
      "uniqueConstraints": {
        "app_settings_key_unique": {
          "name": "app_settings_key_unique",
          "nullsNotDistinct": false,
          "columns": [
            "key"
          ]
        }
      },
      "policies": {},
      "checkConstraints": {},
      "isRLSEnabled": false
    },
    "public.permissions": {
      "name": "permissions",
      "schema": "",
      "columns": {
        "id": {
          "name": "id",
          "type": "text",
          "primaryKey": true,
          "notNull": true
        },
        "code": {
          "name": "code",
          "type": "varchar(50)",
          "primaryKey": false,
          "notNull": true
        },
        "description": {
          "name": "description",
          "type": "varchar(255)",
          "primaryKey": false,
          "notNull": false
        },
        "created_at": {
          "name": "created_at",
          "type": "timestamp",
          "primaryKey": false,
          "notNull": false,
          "default": "now()"
        },
        "updated_at": {
          "name": "updated_at",
          "type": "timestamp",
          "primaryKey": false,
          "notNull": false,
          "default": "now()"
        }
      },
      "indexes": {},
      "foreignKeys": {},
      "compositePrimaryKeys": {},
      "uniqueConstraints": {
        "permissions_code_unique": {
          "name": "permissions_code_unique",
          "nullsNotDistinct": false,
          "columns": [
            "code"
          ]
        }
      },
      "policies": {},
      "checkConstraints": {},
      "isRLSEnabled": false
    },
    "public.permissions_to_roles": {
      "name": "permissions_to_roles",
      "schema": "",
      "columns": {
        "roleId": {
          "name": "roleId",
          "type": "text",
          "primaryKey": false,
          "notNull": true
        },
        "permissionId": {
          "name": "permissionId",
          "type": "text",
          "primaryKey": false,
          "notNull": true
        }
      },
      "indexes": {},
      "foreignKeys": {
        "permissions_to_roles_roleId_roles_id_fk": {
          "name": "permissions_to_roles_roleId_roles_id_fk",
          "tableFrom": "permissions_to_roles",
          "tableTo": "roles",
          "columnsFrom": [
            "roleId"
          ],
          "columnsTo": [
            "id"
          ],
          "onDelete": "cascade",
          "onUpdate": "no action"
        },
        "permissions_to_roles_permissionId_permissions_id_fk": {
          "name": "permissions_to_roles_permissionId_permissions_id_fk",
          "tableFrom": "permissions_to_roles",
          "tableTo": "permissions",
          "columnsFrom": [
            "permissionId"
          ],
          "columnsTo": [
            "id"
          ],
          "onDelete": "cascade",
          "onUpdate": "no action"
        }
      },
      "compositePrimaryKeys": {
        "permissions_to_roles_roleId_permissionId_pk": {
          "name": "permissions_to_roles_roleId_permissionId_pk",
          "columns": [
            "roleId",
            "permissionId"
          ]
        }
      },
      "uniqueConstraints": {},
      "policies": {},
      "checkConstraints": {},
      "isRLSEnabled": false
    },
    "public.permissions_to_users": {
      "name": "permissions_to_users",
      "schema": "",
      "columns": {
        "userId": {
          "name": "userId",
          "type": "text",
          "primaryKey": false,
          "notNull": true
        },
        "permissionId": {
          "name": "permissionId",
          "type": "text",
          "primaryKey": false,
          "notNull": true
        }
      },
      "indexes": {},
      "foreignKeys": {
        "permissions_to_users_userId_users_id_fk": {
          "name": "permissions_to_users_userId_users_id_fk",
          "tableFrom": "permissions_to_users",
          "tableTo": "users",
          "columnsFrom": [
            "userId"
          ],
          "columnsTo": [
            "id"
          ],
          "onDelete": "cascade",
          "onUpdate": "no action"
        },
        "permissions_to_users_permissionId_permissions_id_fk": {
          "name": "permissions_to_users_permissionId_permissions_id_fk",
          "tableFrom": "permissions_to_users",
          "tableTo": "permissions",
          "columnsFrom": [
            "permissionId"
          ],
          "columnsTo": [
            "id"
          ],
          "onDelete": "cascade",
          "onUpdate": "no action"
        }
      },
      "compositePrimaryKeys": {
        "permissions_to_users_userId_permissionId_pk": {
          "name": "permissions_to_users_userId_permissionId_pk",
          "columns": [
            "userId",
            "permissionId"
          ]
        }
      },
      "uniqueConstraints": {},
      "policies": {},
      "checkConstraints": {},
      "isRLSEnabled": false
    },
    "public.roles": {
      "name": "roles",
      "schema": "",
      "columns": {
        "id": {
          "name": "id",
          "type": "text",
          "primaryKey": true,
          "notNull": true
        },
        "code": {
          "name": "code",
          "type": "varchar(50)",
          "primaryKey": false,
          "notNull": true
        },
        "name": {
          "name": "name",
          "type": "varchar(255)",
          "primaryKey": false,
          "notNull": true
        },
        "description": {
          "name": "description",
          "type": "varchar(255)",
          "primaryKey": false,
          "notNull": false
        },
        "created_at": {
          "name": "created_at",
          "type": "timestamp",
          "primaryKey": false,
          "notNull": false,
          "default": "now()"
        },
        "updated_at": {
          "name": "updated_at",
          "type": "timestamp",
          "primaryKey": false,
          "notNull": false,
          "default": "now()"
        }
      },
      "indexes": {},
      "foreignKeys": {},
      "compositePrimaryKeys": {},
      "uniqueConstraints": {
        "roles_code_unique": {
          "name": "roles_code_unique",
          "nullsNotDistinct": false,
          "columns": [
            "code"
          ]
        }
      },
      "policies": {},
      "checkConstraints": {},
      "isRLSEnabled": false
    },
    "public.roles_to_users": {
      "name": "roles_to_users",
      "schema": "",
      "columns": {
        "userId": {
          "name": "userId",
          "type": "text",
          "primaryKey": false,
          "notNull": true
        },
        "roleId": {
          "name": "roleId",
          "type": "text",
          "primaryKey": false,
          "notNull": true
        }
      },
      "indexes": {},
      "foreignKeys": {
        "roles_to_users_userId_users_id_fk": {
          "name": "roles_to_users_userId_users_id_fk",
          "tableFrom": "roles_to_users",
          "tableTo": "users",
          "columnsFrom": [
            "userId"
          ],
          "columnsTo": [
            "id"
          ],
          "onDelete": "cascade",
          "onUpdate": "no action"
        },
        "roles_to_users_roleId_roles_id_fk": {
          "name": "roles_to_users_roleId_roles_id_fk",
          "tableFrom": "roles_to_users",
          "tableTo": "roles",
          "columnsFrom": [
            "roleId"
          ],
          "columnsTo": [
            "id"
          ],
          "onDelete": "cascade",
          "onUpdate": "no action"
        }
      },
      "compositePrimaryKeys": {
        "roles_to_users_userId_roleId_pk": {
          "name": "roles_to_users_userId_roleId_pk",
          "columns": [
            "userId",
            "roleId"
          ]
        }
      },
      "uniqueConstraints": {},
      "policies": {},
      "checkConstraints": {},
      "isRLSEnabled": false
    },
    "public.microsoft_users": {
      "name": "microsoft_users",
      "schema": "",
      "columns": {
        "id": {
          "name": "id",
          "type": "varchar(255)",
          "primaryKey": true,
          "notNull": true
        },
        "user_id": {
          "name": "user_id",
          "type": "text",
          "primaryKey": false,
          "notNull": false
        },
        "microsoft_id": {
          "name": "microsoft_id",
          "type": "varchar(255)",
          "primaryKey": false,
          "notNull": true
        },
        "access_token": {
          "name": "access_token",
          "type": "text",
          "primaryKey": false,
          "notNull": true
        }
      },
      "indexes": {},
      "foreignKeys": {
        "microsoft_users_user_id_users_id_fk": {
          "name": "microsoft_users_user_id_users_id_fk",
          "tableFrom": "microsoft_users",
          "tableTo": "users",
          "columnsFrom": [
            "user_id"
          ],
          "columnsTo": [
            "id"
          ],
          "onDelete": "no action",
          "onUpdate": "no action"
        }
      },
      "compositePrimaryKeys": {},
      "uniqueConstraints": {},
      "policies": {},
      "checkConstraints": {},
      "isRLSEnabled": false
    },
    "public.users": {
      "name": "users",
      "schema": "",
      "columns": {
        "id": {
          "name": "id",
          "type": "text",
          "primaryKey": true,
          "notNull": true
        },
        "name": {
          "name": "name",
          "type": "varchar(255)",
          "primaryKey": false,
          "notNull": true
        },
        "username": {
          "name": "username",
          "type": "varchar",
          "primaryKey": false,
          "notNull": true
        },
        "email": {
          "name": "email",
          "type": "varchar",
          "primaryKey": false,
          "notNull": false
        },
        "password": {
          "name": "password",
          "type": "text",
          "primaryKey": false,
          "notNull": true
        },
        "job_title": {
          "name": "job_title",
          "type": "varchar(255)",
          "primaryKey": false,
          "notNull": false
        },
        "is_enable": {
          "name": "is_enable",
          "type": "boolean",
          "primaryKey": false,
          "notNull": false,
          "default": true
        },
        "created_at": {
          "name": "created_at",
          "type": "timestamp",
          "primaryKey": false,
          "notNull": false,
          "default": "now()"
        },
        "updated_at": {
          "name": "updated_at",
          "type": "timestamp",
          "primaryKey": false,
          "notNull": false,
          "default": "now()"
        },
        "deleted_at": {
          "name": "deleted_at",
          "type": "timestamp",
          "primaryKey": false,
          "notNull": false
        }
      },
      "indexes": {},
      "foreignKeys": {},
      "compositePrimaryKeys": {},
      "uniqueConstraints": {
        "users_username_unique": {
          "name": "users_username_unique",
          "nullsNotDistinct": false,
          "columns": [
            "username"
          ]
        }
      },
      "policies": {},
      "checkConstraints": {},
      "isRLSEnabled": false
    }
  },
  "enums": {},
  "schemas": {},
  "sequences": {},
  "roles": {},
  "policies": {},
  "views": {},
  "_meta": {
    "columns": {},
    "schemas": {},
    "tables": {}
  }
}